rrat.py
setup.py
rrat.egg-info/PKG-INFO
rrat.egg-info/SOURCES.txt
rrat.egg-info/dependency_links.txt
rrat.egg-info/entry_points.txt
rrat.egg-info/top_level.txt