Metadata-Version: 1.1
Name: rrat
Version: 0.6
Summary: Ribosomal RNA Allele Tree
Home-page: https://github.com/crosenth/rrat
Author: Chris Rosenthal
Author-email: crosenth@gmail.com
License: GPLv3
Keywords: ncbi,rrndb,genetics,genomics
Platform: UNKNOWN
Classifier: License :: OSI Approved :: GNU General Public License v3 (GPLv3)
Classifier: Development Status :: 4 - Beta
Classifier: Environment :: Console
Classifier: Operating System :: OS Independent
Classifier: Intended Audience :: End Users/Desktop
Classifier: License :: OSI Approved :: GNU General Public License v3 (GPLv3)
Classifier: Programming Language :: Python :: 3 :: Only
